maplib-0.19.5.dist-info/METADATA
maplib-0.19.5.dist-info/WHEEL
maplib-0.19.5.dist-info/licenses/LICENSE
maplib/.gitignore
maplib/__init__.py
maplib/__init__.pyi
maplib/adding_triples.py
maplib/maplib.abi3.so
maplib/py.typed
maplib/template_generator/__init__.py
maplib/template_generator/generate.py
maplib/template_generator/ordering.py
maplib-0.19.5.dist-info/RECORD
