Metadata-Version: 2.4
Name: maplib
Version: 0.19.5
Classifier: Development Status :: 4 - Beta
Classifier: License :: OSI Approved :: Apache Software License
Classifier: Programming Language :: Python :: 3 :: Only
Classifier: Programming Language :: Python :: 3.9
Classifier: Programming Language :: Python :: 3.10
Classifier: Programming Language :: Python :: 3.11
Classifier: Programming Language :: Rust
Classifier: Topic :: Database :: Database Engines/Servers
Classifier: Topic :: Scientific/Engineering
Requires-Dist: polars>=0.20.13
Requires-Dist: pyarrow>=7.0.0
Requires-Dist: fastapi[standard]>=0.115
License-File: LICENSE
Summary: Dataframe-based interactive knowledge graph construction
Keywords: rdf,graph,dataframe,sparql,ottr
Author-email: Magnus Bakken <magnus@data-treehouse.com>
Requires-Python: >=3.9
Project-URL: Homepage, https://github.com/DataTreehouse/maplib
Project-URL: Documentation, https://datatreehouse.github.io/maplib/maplib/maplib.html
Project-URL: Repository, https://github.com/DataTreehouse/maplib
Project-URL: Changelog, https://github.com/DataTreehouse/maplib/releases
